jarvis/__init__.py
jarvis/config.py
jarvis/jarvis.py
jarvis/personal_assistant.py
jarvis/phrases.py
jarvis_assistant-0.1.3.dist-info/LICENSE
jarvis_assistant-0.1.3.dist-info/METADATA
jarvis_assistant-0.1.3.dist-info/WHEEL
jarvis_assistant-0.1.3.dist-info/top_level.txt
jarvis_assistant-0.1.3.dist-info/RECORD
