Metadata-Version: 2.1
Name: jarvis-assistant
Version: 0.1.3
Summary: Jarvis - Voice Personal Assistant
Home-page: https://github.com/MichalKacprzak99/jarvis
Author: Michał Kacprzak
Author-email: michal.kacprzak999@gmail.com
License: MIT License
Project-URL: Bug Reports, https://github.com/MichalKacprzak99/jarvis/issues
Project-URL: Source, https://github.com/MichalKacprzak99/jarvis
Keywords: python3,jarvis,development,text-to-speech,speech-to-text
Platform: UNKNOWN
Classifier: Development Status :: 5 - Production/Stable
Classifier: Programming Language :: Python
Classifier: Programming Language :: Python :: 3 :: Only
Classifier: Programming Language :: Python :: 3.6
Classifier: License :: OSI Approved :: MIT License
Classifier: Operating System :: Microsoft :: Windows
Classifier: Natural Language :: English
Classifier: Intended Audience :: Developers
Classifier: Intended Audience :: Education
Classifier: Topic :: Home Automation
Classifier: Topic :: Education
Classifier: Topic :: Software Development :: Libraries :: Python Modules
Classifier: Topic :: Text Processing
Classifier: Topic :: Multimedia :: Sound/Audio :: Speech
Requires-Python: >=3.6
Requires-Dist: playsound
Requires-Dist: gTTS
Requires-Dist: requests
Requires-Dist: pyjokes (==0.6.0)
Requires-Dist: pyttsx3
Requires-Dist: numpy
Requires-Dist: pytemperature
Requires-Dist: wikipedia
Requires-Dist: textblob
Requires-Dist: pymongo
Requires-Dist: nltk
Requires-Dist: SpeechRecognition
Requires-Dist: pyaudio
Requires-Dist: python-dotenv
